datedays/__init__.py
datedays/datedays.py
test/__init__.py
test/test.py
datedays-2.2.8.dist-info/LICENSE
datedays-2.2.8.dist-info/METADATA
datedays-2.2.8.dist-info/WHEEL
datedays-2.2.8.dist-info/top_level.txt
datedays-2.2.8.dist-info/RECORD
