Metadata-Version: 2.1
Name: datedays
Version: 2.2.8
Summary: Python Date Tools
Home-page: https://github.com/liang1024/datedays
Author: JiuLiang
Author-email: jiuliange@foxmail.com
Classifier: Programming Language :: Python :: 3
Classifier: License :: OSI Approved :: MIT License
Classifier: Operating System :: OS Independent
License-File: LICENSE
Requires-Dist: openpyxl >=3.0.10
Requires-Dist: xlrd >=2.0.1
Requires-Dist: pycryptodomex >=3.15.0
Requires-Dist: python-dateutil >=2.8.2
